setup.py
traceback.py
micropython_traceback.egg-info/PKG-INFO
micropython_traceback.egg-info/SOURCES.txt
micropython_traceback.egg-info/dependency_links.txt
micropython_traceback.egg-info/top_level.txt